isOdd/__init__.py
isOdd/is_odd.py
IsNumberOdd-1.0.0.dist-info/METADATA
IsNumberOdd-1.0.0.dist-info/WHEEL
IsNumberOdd-1.0.0.dist-info/top_level.txt
IsNumberOdd-1.0.0.dist-info/RECORD
