Metadata-Version: 2.1
Name: IsNumberOdd
Version: 1.0.0
Summary: Return true if the given number is odd.
Home-page: https://github.com/GabouKing/IsOdd
Author: Gabriel R Amaral
Author-email: professor.gabriel.amaral@gmail.com
License: MIT
Platform: UNKNOWN
Classifier: Development Status :: 3 - Alpha
Classifier: Intended Audience :: Developers
Classifier: License :: OSI Approved :: MIT License
Classifier: Programming Language :: Python :: 3
Classifier: Programming Language :: Python :: 3.6
Classifier: Programming Language :: Python :: 3.7
Classifier: Programming Language :: Python :: 3.8
Classifier: Programming Language :: Python :: 3.9
Requires-Dist: IsNumberEven
